{
  "schemaVersion": 1,
  "id": "modid",
  "version": "${version}",

  "name": "FirstMod",
  "description": "First mod by Firestar4204",
  "authors": [
    "Firestar4204"
  ],
  "contact": {
    "homepage": "https://firestar4204.github.io/firstmod",
    "sources": "https://github.com/firestar4204/firstmod"
  },

  "license": "BSD-3-Clause",
  "icon": "assets/modid/icon.png",

  "environment": "*",
  "entrypoints": {
    "main": [
      "io.github.firestar4204.firstmod.FirstMod"
    ]
  },
  "mixins": [
    "modid.mixins.json"
  ],

  "depends": {
    "fabricloader": ">=0.11.3",
    "fabric": "*",
    "minecraft": "1.17.x",
    "java": ">=16"
  },
  "suggests": {
    "another-mod": "*"
  }
}
